ai/__init__.py
ai/ai.py
plutofreeai-0.1.0.dist-info/METADATA
plutofreeai-0.1.0.dist-info/WHEEL
plutofreeai-0.1.0.dist-info/top_level.txt
plutofreeai-0.1.0.dist-info/RECORD
